{
 "_source": "有知有行《中国资产分类投资年鉴 2025》附录2/附表3.2 年度收益 (youzhiyouxing.cn/sbbi2025/appendix, 取数 2026-07-12)。数值为小数收益率;长期信用债自 2007 年起。转录校验:各列 2005-2025 年化与年报声明值逐一核对(见 tests.py)。",
 "_map": {
  "权益": "A股整体",
  "债券类固收": "长期国债",
  "现金": "短期国债",
  "黄金": "上海金"
 },
 "years": {
  "2005": {
   "A股整体": -0.0943,
   "大盘股": -0.0525,
   "小盘股": -0.1499,
   "长期国债": 0.1423,
   "短期国债": 0.0246,
   "上海金": 0.131,
   "通胀": 0.018,
   "长期信用债": null
  },
  "2006": {
   "A股整体": 1.1538,
   "大盘股": 1.2523,
   "小盘股": 0.7673,
   "长期国债": 0.031,
   "短期国债": 0.018,
   "上海金": 0.1931,
   "通胀": 0.0151,
   "长期信用债": null
  },
  "2007": {
   "A股整体": 1.724,
   "大盘股": 1.6328,
   "小盘股": 2.031,
   "长期国债": -0.0526,
   "短期国债": 0.0199,
   "上海金": 0.224,
   "通胀": 0.048,
   "长期信用债": -0.0446
  },
  "2008": {
   "A股整体": -0.6377,
   "大盘股": -0.6561,
   "小盘股": -0.5919,
   "长期国债": 0.1964,
   "短期国债": 0.0439,
   "上海金": -0.0225,
   "通胀": 0.059,
   "长期信用债": 0.1791
  },
  "2009": {
   "A股整体": 1.081,
   "大盘股": 0.9858,
   "小盘股": 1.4044,
   "长期国债": -0.0331,
   "短期国债": 0.0115,
   "上海金": 0.2825,
   "通胀": -0.0071,
   "长期信用债": -0.0164
  },
  "2010": {
   "A股整体": -0.0299,
   "大盘股": -0.1158,
   "小盘股": 0.1764,
   "长期国债": 0.0164,
   "短期国债": 0.0095,
   "上海金": 0.2344,
   "通胀": 0.0329,
   "长期信用债": 0.0406
  },
  "2011": {
   "A股整体": -0.2732,
   "大盘股": -0.2405,
   "小盘股": -0.3278,
   "长期国债": 0.0706,
   "短期国债": 0.0335,
   "上海金": 0.0596,
   "通胀": 0.0539,
   "长期信用债": 0.0407
  },
  "2012": {
   "A股整体": 0.0624,
   "大盘股": 0.098,
   "小盘股": -0.0077,
   "长期国债": 0.0267,
   "短期国债": 0.0265,
   "上海金": 0.046,
   "通胀": 0.026,
   "长期信用债": 0.0508
  },
  "2013": {
   "A股整体": 0.071,
   "大盘股": -0.0533,
   "小盘股": 0.325,
   "长期国债": -0.0354,
   "短期国债": 0.0253,
   "上海金": -0.2931,
   "通胀": 0.026,
   "长期信用债": -0.0124
  },
  "2014": {
   "A股整体": 0.4841,
   "大盘股": 0.5585,
   "小盘股": 0.3526,
   "长期国债": 0.1143,
   "短期国债": 0.0393,
   "上海金": 0.0175,
   "通胀": 0.02,
   "长期信用债": 0.1485
  },
  "2015": {
   "A股整体": 0.3378,
   "大盘股": 0.0722,
   "小盘股": 0.7659,
   "长期国债": 0.0903,
   "短期国债": 0.03,
   "上海金": -0.0737,
   "通胀": 0.014,
   "长期信用债": 0.1396
  },
  "2016": {
   "A股整体": -0.1331,
   "大盘股": -0.0926,
   "小盘股": -0.1969,
   "长期国债": 0.0186,
   "短期国债": 0.0208,
   "上海金": 0.1842,
   "通胀": 0.02,
   "长期信用债": 0.007
  },
  "2017": {
   "A股整体": 0.0368,
   "大盘股": 0.2425,
   "小盘股": -0.1689,
   "长期国债": -0.0294,
   "短期国债": 0.0276,
   "上海金": 0.0345,
   "通胀": 0.0159,
   "长期信用债": -0.0177
  },
  "2018": {
   "A股整体": -0.2879,
   "大盘股": -0.2364,
   "小盘股": -0.3628,
   "长期国债": 0.0867,
   "短期国债": 0.0357,
   "上海金": 0.0425,
   "通胀": 0.021,
   "长期信用债": 0.1162
  },
  "2019": {
   "A股整体": 0.3341,
   "大盘股": 0.3919,
   "小盘股": 0.2698,
   "长期国债": 0.044,
   "短期国债": 0.0275,
   "上海金": 0.1975,
   "通胀": 0.029,
   "长期信用债": 0.0598
  },
  "2020": {
   "A股整体": 0.2687,
   "大盘股": 0.2989,
   "小盘股": 0.2045,
   "长期国债": 0.0252,
   "短期国债": 0.02,
   "上海金": 0.1444,
   "通胀": 0.0249,
   "长期信用债": 0.044
  },
  "2021": {
   "A股整体": 0.077,
   "大盘股": -0.0352,
   "小盘股": 0.2161,
   "长期国债": 0.0576,
   "短期国债": 0.0246,
   "上海金": -0.0414,
   "通胀": 0.009,
   "长期信用债": 0.0676
  },
  "2022": {
   "A股整体": -0.1893,
   "大盘股": -0.1984,
   "小盘股": -0.2077,
   "长期国债": 0.03,
   "短期国债": 0.0194,
   "上海金": 0.098,
   "通胀": 0.0201,
   "长期信用债": 0.0324
  },
  "2023": {
   "A股整体": -0.0534,
   "大盘股": -0.0914,
   "小盘股": -0.0528,
   "长期国债": 0.048,
   "短期国债": 0.0209,
   "上海金": 0.1683,
   "通胀": 0.002,
   "长期信用债": 0.0774
  },
  "2024": {
   "A股整体": 0.0998,
   "大盘股": 0.1824,
   "小盘股": 0.0279,
   "长期国债": 0.0938,
   "短期国债": 0.02,
   "上海金": 0.2819,
   "通胀": 0.002,
   "长期信用债": 0.1022
  },
  "2025": {
   "A股整体": 0.2703,
   "大盘股": 0.2098,
   "小盘股": 0.2902,
   "长期国债": 0.0089,
   "短期国债": 0.0123,
   "上海金": 0.5857,
   "通胀": 0.0,
   "长期信用债": 0.003
  }
 }
}